LICENSE
README.rst
pyproject.toml
pytest_freezer.py
tests/conftest.py
tests/test_plugin.py
pytest_freezer-0.4.7.dist-info/METADATA
pytest_freezer-0.4.7.dist-info/WHEEL
pytest_freezer-0.4.7.dist-info/entry_points.txt
pytest_freezer-0.4.7.dist-info/licenses/LICENSE
pytest_freezer-0.4.7.dist-info/RECORD
