Metadata-Version: 2.1
Name: pytest_freezer
Version: 0.4.7
Summary: Pytest plugin providing a fixture interface for spulec/freezegun
Project-URL: Homepage, https://github.com/pytest-dev/pytest-freezer
Author-email: Wim Glenn <hey@wimglenn.com>
License-Expression: MIT
License-File: LICENSE
Classifier: Framework :: Pytest
Classifier: License :: OSI Approved :: MIT License
Requires-Python: >=3.6
Requires-Dist: freezegun>=1.0
Requires-Dist: pytest>=3.6
